examples/__init__.py
examples/data_handler.py
examples/data_utils.py
examples/scn_data_module.py
examples/train_lightning.py
geometric_vector_perceptron/__init__.py
geometric_vector_perceptron/geometric_vector_perceptron.py
geometric_vector_perceptron-0.0.14.dist-info/LICENSE
geometric_vector_perceptron-0.0.14.dist-info/METADATA
geometric_vector_perceptron-0.0.14.dist-info/WHEEL
geometric_vector_perceptron-0.0.14.dist-info/top_level.txt
geometric_vector_perceptron-0.0.14.dist-info/RECORD
