Metadata-Version: 2.1
Name: geometric-vector-perceptron
Version: 0.0.14
Summary: Geometric Vector Perceptron - Pytorch
Home-page: https://github.com/lucidrains/geometric-vector-perceptron
Author: Phil Wang, Eric Alcaide
Author-email: lucidrains@gmail.com
License: MIT
Keywords: artificial intelligence,deep learning,proteins,biomolecules,equivariance
Platform: UNKNOWN
Classifier: Development Status :: 4 - Beta
Classifier: Intended Audience :: Developers
Classifier: Topic :: Scientific/Engineering :: Artificial Intelligence
Classifier: License :: OSI Approved :: MIT License
Classifier: Programming Language :: Python :: 3.6
Requires-Dist: torch (>=1.6)
Requires-Dist: torch-scatter
Requires-Dist: torch-sparse
Requires-Dist: torch-cluster
Requires-Dist: torch-spline-conv
Requires-Dist: torch-geometric
